<?xml version="1.0" encoding="utf-8"?>
<surrogateModel xmlns="http://purl.org/NET/prime/" xmlns:xsi="http://www.w3.org/2001/XMLSchema-instance" primeID="sm00000009" type="quadratic" xsi:schemaLocation="http://purl.org/NET/prime/ http://warehouse.primekinetics.org/schema/surrogateModel.xsd">
  <copyright>©primekinetics.org 2010</copyright>
  <preferredKey group="prime">PrIMe H2 1.0 - flw4</preferredKey>
  <dataAttributeLink preferredKey="PrIMe H2 1.0 - flw4" primeID="a00000100" transformation="log10" weight="1" />
  <datasetLink preferredKey="PrIMe H2 1.0 dataset" primeID="d00000002" />
  <optimizationVariables>
    <optimizationVariableLink boundsPrimeID="vb00000001" id="1" preferredKey="A(HO2 + H &lt;=&gt; H2 + O2)" primeID="v00000132" />
    <optimizationVariableLink boundsPrimeID="vb00000001" id="2" preferredKey="A(H + O &lt;=&gt; OH)" primeID="v00000129" />
    <optimizationVariableLink boundsPrimeID="vb00000001" id="3" preferredKey="A(HO2 + O &lt;=&gt; OH + O2)" primeID="v00000131" />
    <optimizationVariableLink boundsPrimeID="vb00000001" id="4" preferredKey="A(HO2 + H &lt;=&gt; H2O + O)" primeID="v00000130" />
    <optimizationVariableLink boundsPrimeID="vb00000001" id="5" preferredKey="A(2 H &lt;=&gt; H2)" primeID="v00000119" />
    <optimizationVariableLink boundsPrimeID="vb00000001" id="6" preferredKey="A(O + H2O2 &lt;=&gt; OH + HO2)" primeID="v00000126" />
    <optimizationVariableLink boundsPrimeID="vb00000001" id="7" preferredKey="A(O2 + H &lt;=&gt; OH + O)" primeID="v00000014" />
    <optimizationVariableLink boundsPrimeID="vb00000001" id="8" preferredKey="A(O2 + H &lt;=&gt; HO2)" primeID="v00000118" />
    <optimizationVariableLink boundsPrimeID="vb00000001" id="9" preferredKey="A(H2O2 + H &lt;=&gt; H2 + HO2)" primeID="v00000125" />
    <optimizationVariableLink boundsPrimeID="vb00000001" id="10" preferredKey="A(2 HO2 &lt;=&gt; H2O2 + O2)" primeID="v00000123" />
    <optimizationVariableLink boundsPrimeID="vb00000001" id="11" preferredKey="A(2 OH &lt;=&gt; H2O + O)" primeID="v00000035" />
    <optimizationVariableLink boundsPrimeID="vb00000001" id="12" preferredKey="A(O + OH &lt;=&gt; HO2)" primeID="v00000133" />
    <optimizationVariableLink boundsPrimeID="vb00000002" id="13" preferredKey="A(HO2 + H &lt;=&gt; 2 OH)" primeID="v00000018" />
    <optimizationVariableLink boundsPrimeID="vb00000001" id="14" preferredKey="A(2 OH &lt;=&gt; H2O2)" primeID="v00000134" />
    <optimizationVariableLink boundsPrimeID="vb00000001" id="15" preferredKey="A(H2O2 + H &lt;=&gt; OH + H2O)" primeID="v00000124" />
    <optimizationVariableLink boundsPrimeID="vb00000001" id="16" preferredKey="A(OH + H2O2 &lt;=&gt; HO2 + H2O)" primeID="v00000127" />
    <optimizationVariableLink boundsPrimeID="vb00000001" id="17" preferredKey="A(H2 + OH &lt;=&gt; H2O + H)" primeID="v00000033" />
  </optimizationVariables>
  <coefficient>
    <variables>
      <variableLink>0</variableLink>
      <variableLink>0</variableLink>
    </variables>
    <value>2.53165418</value>
  </coefficient>
  <coefficient>
    <variables>
      <variableLink>1</variableLink>
      <variableLink>0</variableLink>
    </variables>
    <value>-0.0155827718</value>
  </coefficient>
  <coefficient>
    <variables>
      <variableLink>2</variableLink>
      <variableLink>0</variableLink>
    </variables>
    <value>3.88600968e-005</value>
  </coefficient>
  <coefficient>
    <variables>
      <variableLink>3</variableLink>
      <variableLink>0</variableLink>
    </variables>
    <value>-0.00428439972</value>
  </coefficient>
  <coefficient>
    <variables>
      <variableLink>4</variableLink>
      <variableLink>0</variableLink>
    </variables>
    <value>-0.00459660863</value>
  </coefficient>
  <coefficient>
    <variables>
      <variableLink>5</variableLink>
      <variableLink>0</variableLink>
    </variables>
    <value>-6.69447643e-005</value>
  </coefficient>
  <coefficient>
    <variables>
      <variableLink>6</variableLink>
      <variableLink>0</variableLink>
    </variables>
    <value>-6.57717921e-006</value>
  </coefficient>
  <coefficient>
    <variables>
      <variableLink>7</variableLink>
      <variableLink>0</variableLink>
    </variables>
    <value>0.0256555096</value>
  </coefficient>
  <coefficient>
    <variables>
      <variableLink>8</variableLink>
      <variableLink>0</variableLink>
    </variables>
    <value>-0.0194103245</value>
  </coefficient>
  <coefficient>
    <variables>
      <variableLink>9</variableLink>
      <variableLink>0</variableLink>
    </variables>
    <value>-1.66400582e-005</value>
  </coefficient>
  <coefficient>
    <variables>
      <variableLink>10</variableLink>
      <variableLink>0</variableLink>
    </variables>
    <value>-5.43588306e-005</value>
  </coefficient>
  <coefficient>
    <variables>
      <variableLink>11</variableLink>
      <variableLink>0</variableLink>
    </variables>
    <value>-0.00462019085</value>
  </coefficient>
  <coefficient>
    <variables>
      <variableLink>12</variableLink>
      <variableLink>0</variableLink>
    </variables>
    <value>8.2250584e-006</value>
  </coefficient>
  <coefficient>
    <variables>
      <variableLink>13</variableLink>
      <variableLink>0</variableLink>
    </variables>
    <value>0.0184835445</value>
  </coefficient>
  <coefficient>
    <variables>
      <variableLink>14</variableLink>
      <variableLink>0</variableLink>
    </variables>
    <value>-0.000818316281</value>
  </coefficient>
  <coefficient>
    <variables>
      <variableLink>15</variableLink>
      <variableLink>0</variableLink>
    </variables>
    <value>0.000133099648</value>
  </coefficient>
  <coefficient>
    <variables>
      <variableLink>16</variableLink>
      <variableLink>0</variableLink>
    </variables>
    <value>-7.31992982e-005</value>
  </coefficient>
  <coefficient>
    <variables>
      <variableLink>17</variableLink>
      <variableLink>0</variableLink>
    </variables>
    <value>0.0629082721</value>
  </coefficient>
  <coefficient>
    <variables>
      <variableLink>1</variableLink>
      <variableLink>1</variableLink>
    </variables>
    <value>-0.00141617482</value>
  </coefficient>
  <coefficient>
    <variables>
      <variableLink>1</variableLink>
      <variableLink>2</variableLink>
    </variables>
    <value>2.84186333e-005</value>
  </coefficient>
  <coefficient>
    <variables>
      <variableLink>1</variableLink>
      <variableLink>3</variableLink>
    </variables>
    <value>0.00033773201</value>
  </coefficient>
  <coefficient>
    <variables>
      <variableLink>1</variableLink>
      <variableLink>4</variableLink>
    </variables>
    <value>0.000887030206</value>
  </coefficient>
  <coefficient>
    <variables>
      <variableLink>1</variableLink>
      <variableLink>5</variableLink>
    </variables>
    <value>0.000133261564</value>
  </coefficient>
  <coefficient>
    <variables>
      <variableLink>1</variableLink>
      <variableLink>6</variableLink>
    </variables>
    <value>-0.000126450653</value>
  </coefficient>
  <coefficient>
    <variables>
      <variableLink>1</variableLink>
      <variableLink>7</variableLink>
    </variables>
    <value>0.0013910776</value>
  </coefficient>
  <coefficient>
    <variables>
      <variableLink>1</variableLink>
      <variableLink>8</variableLink>
    </variables>
    <value>-0.00305112706</value>
  </coefficient>
  <coefficient>
    <variables>
      <variableLink>1</variableLink>
      <variableLink>9</variableLink>
    </variables>
    <value>0.000128278516</value>
  </coefficient>
  <coefficient>
    <variables>
      <variableLink>1</variableLink>
      <variableLink>10</variableLink>
    </variables>
    <value>-5.92054933e-005</value>
  </coefficient>
  <coefficient>
    <variables>
      <variableLink>1</variableLink>
      <variableLink>11</variableLink>
    </variables>
    <value>0.00015795358</value>
  </coefficient>
  <coefficient>
    <variables>
      <variableLink>1</variableLink>
      <variableLink>12</variableLink>
    </variables>
    <value>0.000171154081</value>
  </coefficient>
  <coefficient>
    <variables>
      <variableLink>1</variableLink>
      <variableLink>13</variableLink>
    </variables>
    <value>0.00209953113</value>
  </coefficient>
  <coefficient>
    <variables>
      <variableLink>1</variableLink>
      <variableLink>14</variableLink>
    </variables>
    <value>-5.03745781e-006</value>
  </coefficient>
  <coefficient>
    <variables>
      <variableLink>1</variableLink>
      <variableLink>15</variableLink>
    </variables>
    <value>-7.53094505e-006</value>
  </coefficient>
  <coefficient>
    <variables>
      <variableLink>1</variableLink>
      <variableLink>16</variableLink>
    </variables>
    <value>-5.50719626e-005</value>
  </coefficient>
  <coefficient>
    <variables>
      <variableLink>1</variableLink>
      <variableLink>17</variableLink>
    </variables>
    <value>0.000346503289</value>
  </coefficient>
  <coefficient>
    <variables>
      <variableLink>2</variableLink>
      <variableLink>2</variableLink>
    </variables>
    <value>-1.31914025e-005</value>
  </coefficient>
  <coefficient>
    <variables>
      <variableLink>2</variableLink>
      <variableLink>3</variableLink>
    </variables>
    <value>-7.58598569e-005</value>
  </coefficient>
  <coefficient>
    <variables>
      <variableLink>2</variableLink>
      <variableLink>4</variableLink>
    </variables>
    <value>6.9829414e-005</value>
  </coefficient>
  <coefficient>
    <variables>
      <variableLink>2</variableLink>
      <variableLink>5</variableLink>
    </variables>
    <value>-0.000130262012</value>
  </coefficient>
  <coefficient>
    <variables>
      <variableLink>2</variableLink>
      <variableLink>6</variableLink>
    </variables>
    <value>-2.26176044e-005</value>
  </coefficient>
  <coefficient>
    <variables>
      <variableLink>2</variableLink>
      <variableLink>7</variableLink>
    </variables>
    <value>-4.75705422e-005</value>
  </coefficient>
  <coefficient>
    <variables>
      <variableLink>2</variableLink>
      <variableLink>8</variableLink>
    </variables>
    <value>7.8065742e-005</value>
  </coefficient>
  <coefficient>
    <variables>
      <variableLink>2</variableLink>
      <variableLink>9</variableLink>
    </variables>
    <value>7.11690037e-005</value>
  </coefficient>
  <coefficient>
    <variables>
      <variableLink>2</variableLink>
      <variableLink>10</variableLink>
    </variables>
    <value>4.02665133e-005</value>
  </coefficient>
  <coefficient>
    <variables>
      <variableLink>2</variableLink>
      <variableLink>11</variableLink>
    </variables>
    <value>7.26302144e-005</value>
  </coefficient>
  <coefficient>
    <variables>
      <variableLink>2</variableLink>
      <variableLink>12</variableLink>
    </variables>
    <value>-0.000117750799</value>
  </coefficient>
  <coefficient>
    <variables>
      <variableLink>2</variableLink>
      <variableLink>13</variableLink>
    </variables>
    <value>-5.79826954e-005</value>
  </coefficient>
  <coefficient>
    <variables>
      <variableLink>2</variableLink>
      <variableLink>14</variableLink>
    </variables>
    <value>1.7256575e-005</value>
  </coefficient>
  <coefficient>
    <variables>
      <variableLink>2</variableLink>
      <variableLink>15</variableLink>
    </variables>
    <value>-5.0884011e-005</value>
  </coefficient>
  <coefficient>
    <variables>
      <variableLink>2</variableLink>
      <variableLink>16</variableLink>
    </variables>
    <value>-5.18307263e-005</value>
  </coefficient>
  <coefficient>
    <variables>
      <variableLink>2</variableLink>
      <variableLink>17</variableLink>
    </variables>
    <value>-0.000100512556</value>
  </coefficient>
  <coefficient>
    <variables>
      <variableLink>3</variableLink>
      <variableLink>3</variableLink>
    </variables>
    <value>-0.00152802825</value>
  </coefficient>
  <coefficient>
    <variables>
      <variableLink>3</variableLink>
      <variableLink>4</variableLink>
    </variables>
    <value>2.87488258e-005</value>
  </coefficient>
  <coefficient>
    <variables>
      <variableLink>3</variableLink>
      <variableLink>5</variableLink>
    </variables>
    <value>-5.81203679e-006</value>
  </coefficient>
  <coefficient>
    <variables>
      <variableLink>3</variableLink>
      <variableLink>6</variableLink>
    </variables>
    <value>0.000107305761</value>
  </coefficient>
  <coefficient>
    <variables>
      <variableLink>3</variableLink>
      <variableLink>7</variableLink>
    </variables>
    <value>0.000934912108</value>
  </coefficient>
  <coefficient>
    <variables>
      <variableLink>3</variableLink>
      <variableLink>8</variableLink>
    </variables>
    <value>-0.00130960184</value>
  </coefficient>
  <coefficient>
    <variables>
      <variableLink>3</variableLink>
      <variableLink>9</variableLink>
    </variables>
    <value>-3.58682169e-005</value>
  </coefficient>
  <coefficient>
    <variables>
      <variableLink>3</variableLink>
      <variableLink>10</variableLink>
    </variables>
    <value>-2.82403639e-005</value>
  </coefficient>
  <coefficient>
    <variables>
      <variableLink>3</variableLink>
      <variableLink>11</variableLink>
    </variables>
    <value>-3.39259409e-005</value>
  </coefficient>
  <coefficient>
    <variables>
      <variableLink>3</variableLink>
      <variableLink>12</variableLink>
    </variables>
    <value>-9.9850503e-005</value>
  </coefficient>
  <coefficient>
    <variables>
      <variableLink>3</variableLink>
      <variableLink>13</variableLink>
    </variables>
    <value>0.000432398811</value>
  </coefficient>
  <coefficient>
    <variables>
      <variableLink>3</variableLink>
      <variableLink>14</variableLink>
    </variables>
    <value>-9.72042993e-005</value>
  </coefficient>
  <coefficient>
    <variables>
      <variableLink>3</variableLink>
      <variableLink>15</variableLink>
    </variables>
    <value>1.12969318e-005</value>
  </coefficient>
  <coefficient>
    <variables>
      <variableLink>3</variableLink>
      <variableLink>16</variableLink>
    </variables>
    <value>-4.96271987e-005</value>
  </coefficient>
  <coefficient>
    <variables>
      <variableLink>3</variableLink>
      <variableLink>17</variableLink>
    </variables>
    <value>-0.000463783164</value>
  </coefficient>
  <coefficient>
    <variables>
      <variableLink>4</variableLink>
      <variableLink>4</variableLink>
    </variables>
    <value>-0.00220486512</value>
  </coefficient>
  <coefficient>
    <variables>
      <variableLink>4</variableLink>
      <variableLink>5</variableLink>
    </variables>
    <value>-2.45192219e-005</value>
  </coefficient>
  <coefficient>
    <variables>
      <variableLink>4</variableLink>
      <variableLink>6</variableLink>
    </variables>
    <value>1.02569022e-005</value>
  </coefficient>
  <coefficient>
    <variables>
      <variableLink>4</variableLink>
      <variableLink>7</variableLink>
    </variables>
    <value>-0.000340557939</value>
  </coefficient>
  <coefficient>
    <variables>
      <variableLink>4</variableLink>
      <variableLink>8</variableLink>
    </variables>
    <value>-0.000657290411</value>
  </coefficient>
  <coefficient>
    <variables>
      <variableLink>4</variableLink>
      <variableLink>9</variableLink>
    </variables>
    <value>-0.000197996912</value>
  </coefficient>
  <coefficient>
    <variables>
      <variableLink>4</variableLink>
      <variableLink>10</variableLink>
    </variables>
    <value>8.47516632e-006</value>
  </coefficient>
  <coefficient>
    <variables>
      <variableLink>4</variableLink>
      <variableLink>11</variableLink>
    </variables>
    <value>0.000476967352</value>
  </coefficient>
  <coefficient>
    <variables>
      <variableLink>4</variableLink>
      <variableLink>12</variableLink>
    </variables>
    <value>-0.000103620081</value>
  </coefficient>
  <coefficient>
    <variables>
      <variableLink>4</variableLink>
      <variableLink>13</variableLink>
    </variables>
    <value>-0.000356787554</value>
  </coefficient>
  <coefficient>
    <variables>
      <variableLink>4</variableLink>
      <variableLink>14</variableLink>
    </variables>
    <value>4.55704303e-005</value>
  </coefficient>
  <coefficient>
    <variables>
      <variableLink>4</variableLink>
      <variableLink>15</variableLink>
    </variables>
    <value>5.26784482e-005</value>
  </coefficient>
  <coefficient>
    <variables>
      <variableLink>4</variableLink>
      <variableLink>16</variableLink>
    </variables>
    <value>-4.4194885e-005</value>
  </coefficient>
  <coefficient>
    <variables>
      <variableLink>4</variableLink>
      <variableLink>17</variableLink>
    </variables>
    <value>-4.61029015e-006</value>
  </coefficient>
  <coefficient>
    <variables>
      <variableLink>5</variableLink>
      <variableLink>5</variableLink>
    </variables>
    <value>-0.000163374058</value>
  </coefficient>
  <coefficient>
    <variables>
      <variableLink>5</variableLink>
      <variableLink>6</variableLink>
    </variables>
    <value>3.99931245e-005</value>
  </coefficient>
  <coefficient>
    <variables>
      <variableLink>5</variableLink>
      <variableLink>7</variableLink>
    </variables>
    <value>-8.00276619e-005</value>
  </coefficient>
  <coefficient>
    <variables>
      <variableLink>5</variableLink>
      <variableLink>8</variableLink>
    </variables>
    <value>0.000113176501</value>
  </coefficient>
  <coefficient>
    <variables>
      <variableLink>5</variableLink>
      <variableLink>9</variableLink>
    </variables>
    <value>1.78626122e-005</value>
  </coefficient>
  <coefficient>
    <variables>
      <variableLink>5</variableLink>
      <variableLink>10</variableLink>
    </variables>
    <value>0.000123797444</value>
  </coefficient>
  <coefficient>
    <variables>
      <variableLink>5</variableLink>
      <variableLink>11</variableLink>
    </variables>
    <value>5.71607015e-005</value>
  </coefficient>
  <coefficient>
    <variables>
      <variableLink>5</variableLink>
      <variableLink>12</variableLink>
    </variables>
    <value>-3.47685565e-005</value>
  </coefficient>
  <coefficient>
    <variables>
      <variableLink>5</variableLink>
      <variableLink>13</variableLink>
    </variables>
    <value>-0.000105076742</value>
  </coefficient>
  <coefficient>
    <variables>
      <variableLink>5</variableLink>
      <variableLink>14</variableLink>
    </variables>
    <value>0.000150978916</value>
  </coefficient>
  <coefficient>
    <variables>
      <variableLink>5</variableLink>
      <variableLink>15</variableLink>
    </variables>
    <value>-4.98309612e-005</value>
  </coefficient>
  <coefficient>
    <variables>
      <variableLink>5</variableLink>
      <variableLink>16</variableLink>
    </variables>
    <value>3.27611268e-005</value>
  </coefficient>
  <coefficient>
    <variables>
      <variableLink>5</variableLink>
      <variableLink>17</variableLink>
    </variables>
    <value>-0.000113324987</value>
  </coefficient>
  <coefficient>
    <variables>
      <variableLink>6</variableLink>
      <variableLink>6</variableLink>
    </variables>
    <value>7.33624023e-006</value>
  </coefficient>
  <coefficient>
    <variables>
      <variableLink>6</variableLink>
      <variableLink>7</variableLink>
    </variables>
    <value>-1.29807698e-006</value>
  </coefficient>
  <coefficient>
    <variables>
      <variableLink>6</variableLink>
      <variableLink>8</variableLink>
    </variables>
    <value>-4.02907808e-005</value>
  </coefficient>
  <coefficient>
    <variables>
      <variableLink>6</variableLink>
      <variableLink>9</variableLink>
    </variables>
    <value>-3.37510922e-005</value>
  </coefficient>
  <coefficient>
    <variables>
      <variableLink>6</variableLink>
      <variableLink>10</variableLink>
    </variables>
    <value>-1.48141576e-005</value>
  </coefficient>
  <coefficient>
    <variables>
      <variableLink>6</variableLink>
      <variableLink>11</variableLink>
    </variables>
    <value>5.09988859e-005</value>
  </coefficient>
  <coefficient>
    <variables>
      <variableLink>6</variableLink>
      <variableLink>12</variableLink>
    </variables>
    <value>3.56769761e-005</value>
  </coefficient>
  <coefficient>
    <variables>
      <variableLink>6</variableLink>
      <variableLink>13</variableLink>
    </variables>
    <value>5.91769717e-005</value>
  </coefficient>
  <coefficient>
    <variables>
      <variableLink>6</variableLink>
      <variableLink>14</variableLink>
    </variables>
    <value>3.31472267e-005</value>
  </coefficient>
  <coefficient>
    <variables>
      <variableLink>6</variableLink>
      <variableLink>15</variableLink>
    </variables>
    <value>-1.16796314e-005</value>
  </coefficient>
  <coefficient>
    <variables>
      <variableLink>6</variableLink>
      <variableLink>16</variableLink>
    </variables>
    <value>0.000102082219</value>
  </coefficient>
  <coefficient>
    <variables>
      <variableLink>6</variableLink>
      <variableLink>17</variableLink>
    </variables>
    <value>-1.11474076e-005</value>
  </coefficient>
  <coefficient>
    <variables>
      <variableLink>7</variableLink>
      <variableLink>7</variableLink>
    </variables>
    <value>-0.00205806089</value>
  </coefficient>
  <coefficient>
    <variables>
      <variableLink>7</variableLink>
      <variableLink>8</variableLink>
    </variables>
    <value>0.00258311671</value>
  </coefficient>
  <coefficient>
    <variables>
      <variableLink>7</variableLink>
      <variableLink>9</variableLink>
    </variables>
    <value>1.12846481e-005</value>
  </coefficient>
  <coefficient>
    <variables>
      <variableLink>7</variableLink>
      <variableLink>10</variableLink>
    </variables>
    <value>0.000142607268</value>
  </coefficient>
  <coefficient>
    <variables>
      <variableLink>7</variableLink>
      <variableLink>11</variableLink>
    </variables>
    <value>-0.000317192659</value>
  </coefficient>
  <coefficient>
    <variables>
      <variableLink>7</variableLink>
      <variableLink>12</variableLink>
    </variables>
    <value>7.37484838e-006</value>
  </coefficient>
  <coefficient>
    <variables>
      <variableLink>7</variableLink>
      <variableLink>13</variableLink>
    </variables>
    <value>-0.00190821652</value>
  </coefficient>
  <coefficient>
    <variables>
      <variableLink>7</variableLink>
      <variableLink>14</variableLink>
    </variables>
    <value>-8.23592881e-005</value>
  </coefficient>
  <coefficient>
    <variables>
      <variableLink>7</variableLink>
      <variableLink>15</variableLink>
    </variables>
    <value>-0.000120082003</value>
  </coefficient>
  <coefficient>
    <variables>
      <variableLink>7</variableLink>
      <variableLink>16</variableLink>
    </variables>
    <value>-5.94383553e-005</value>
  </coefficient>
  <coefficient>
    <variables>
      <variableLink>7</variableLink>
      <variableLink>17</variableLink>
    </variables>
    <value>0.00261421604</value>
  </coefficient>
  <coefficient>
    <variables>
      <variableLink>8</variableLink>
      <variableLink>8</variableLink>
    </variables>
    <value>-0.0031484909</value>
  </coefficient>
  <coefficient>
    <variables>
      <variableLink>8</variableLink>
      <variableLink>9</variableLink>
    </variables>
    <value>9.95830503e-005</value>
  </coefficient>
  <coefficient>
    <variables>
      <variableLink>8</variableLink>
      <variableLink>10</variableLink>
    </variables>
    <value>-6.5377106e-005</value>
  </coefficient>
  <coefficient>
    <variables>
      <variableLink>8</variableLink>
      <variableLink>11</variableLink>
    </variables>
    <value>-0.000432329521</value>
  </coefficient>
  <coefficient>
    <variables>
      <variableLink>8</variableLink>
      <variableLink>12</variableLink>
    </variables>
    <value>5.00309923e-005</value>
  </coefficient>
  <coefficient>
    <variables>
      <variableLink>8</variableLink>
      <variableLink>13</variableLink>
    </variables>
    <value>0.0040602016</value>
  </coefficient>
  <coefficient>
    <variables>
      <variableLink>8</variableLink>
      <variableLink>14</variableLink>
    </variables>
    <value>-0.00016788838</value>
  </coefficient>
  <coefficient>
    <variables>
      <variableLink>8</variableLink>
      <variableLink>15</variableLink>
    </variables>
    <value>5.52642769e-005</value>
  </coefficient>
  <coefficient>
    <variables>
      <variableLink>8</variableLink>
      <variableLink>16</variableLink>
    </variables>
    <value>7.33395758e-005</value>
  </coefficient>
  <coefficient>
    <variables>
      <variableLink>8</variableLink>
      <variableLink>17</variableLink>
    </variables>
    <value>0.00218751405</value>
  </coefficient>
  <coefficient>
    <variables>
      <variableLink>9</variableLink>
      <variableLink>9</variableLink>
    </variables>
    <value>2.02848322e-005</value>
  </coefficient>
  <coefficient>
    <variables>
      <variableLink>9</variableLink>
      <variableLink>10</variableLink>
    </variables>
    <value>5.11527771e-005</value>
  </coefficient>
  <coefficient>
    <variables>
      <variableLink>9</variableLink>
      <variableLink>11</variableLink>
    </variables>
    <value>0.00011356265</value>
  </coefficient>
  <coefficient>
    <variables>
      <variableLink>9</variableLink>
      <variableLink>12</variableLink>
    </variables>
    <value>-3.45869568e-005</value>
  </coefficient>
  <coefficient>
    <variables>
      <variableLink>9</variableLink>
      <variableLink>13</variableLink>
    </variables>
    <value>-2.6897632e-005</value>
  </coefficient>
  <coefficient>
    <variables>
      <variableLink>9</variableLink>
      <variableLink>14</variableLink>
    </variables>
    <value>-0.000146617079</value>
  </coefficient>
  <coefficient>
    <variables>
      <variableLink>9</variableLink>
      <variableLink>15</variableLink>
    </variables>
    <value>6.25063501e-005</value>
  </coefficient>
  <coefficient>
    <variables>
      <variableLink>9</variableLink>
      <variableLink>16</variableLink>
    </variables>
    <value>4.22820327e-005</value>
  </coefficient>
  <coefficient>
    <variables>
      <variableLink>9</variableLink>
      <variableLink>17</variableLink>
    </variables>
    <value>2.68511917e-006</value>
  </coefficient>
  <coefficient>
    <variables>
      <variableLink>10</variableLink>
      <variableLink>10</variableLink>
    </variables>
    <value>-4.8151441e-005</value>
  </coefficient>
  <coefficient>
    <variables>
      <variableLink>10</variableLink>
      <variableLink>11</variableLink>
    </variables>
    <value>1.10422367e-005</value>
  </coefficient>
  <coefficient>
    <variables>
      <variableLink>10</variableLink>
      <variableLink>12</variableLink>
    </variables>
    <value>0.000140937135</value>
  </coefficient>
  <coefficient>
    <variables>
      <variableLink>10</variableLink>
      <variableLink>13</variableLink>
    </variables>
    <value>8.98926913e-005</value>
  </coefficient>
  <coefficient>
    <variables>
      <variableLink>10</variableLink>
      <variableLink>14</variableLink>
    </variables>
    <value>2.03050045e-005</value>
  </coefficient>
  <coefficient>
    <variables>
      <variableLink>10</variableLink>
      <variableLink>15</variableLink>
    </variables>
    <value>-8.75175678e-005</value>
  </coefficient>
  <coefficient>
    <variables>
      <variableLink>10</variableLink>
      <variableLink>16</variableLink>
    </variables>
    <value>-7.87270845e-005</value>
  </coefficient>
  <coefficient>
    <variables>
      <variableLink>10</variableLink>
      <variableLink>17</variableLink>
    </variables>
    <value>-7.74640072e-006</value>
  </coefficient>
  <coefficient>
    <variables>
      <variableLink>11</variableLink>
      <variableLink>11</variableLink>
    </variables>
    <value>-0.0009320481</value>
  </coefficient>
  <coefficient>
    <variables>
      <variableLink>11</variableLink>
      <variableLink>12</variableLink>
    </variables>
    <value>-7.55941123e-005</value>
  </coefficient>
  <coefficient>
    <variables>
      <variableLink>11</variableLink>
      <variableLink>13</variableLink>
    </variables>
    <value>-0.000257162093</value>
  </coefficient>
  <coefficient>
    <variables>
      <variableLink>11</variableLink>
      <variableLink>14</variableLink>
    </variables>
    <value>5.39165606e-006</value>
  </coefficient>
  <coefficient>
    <variables>
      <variableLink>11</variableLink>
      <variableLink>15</variableLink>
    </variables>
    <value>4.77088101e-005</value>
  </coefficient>
  <coefficient>
    <variables>
      <variableLink>11</variableLink>
      <variableLink>16</variableLink>
    </variables>
    <value>-5.37597782e-005</value>
  </coefficient>
  <coefficient>
    <variables>
      <variableLink>11</variableLink>
      <variableLink>17</variableLink>
    </variables>
    <value>0.00181203647</value>
  </coefficient>
  <coefficient>
    <variables>
      <variableLink>12</variableLink>
      <variableLink>12</variableLink>
    </variables>
    <value>-1.17984049e-005</value>
  </coefficient>
  <coefficient>
    <variables>
      <variableLink>12</variableLink>
      <variableLink>13</variableLink>
    </variables>
    <value>-8.25699068e-005</value>
  </coefficient>
  <coefficient>
    <variables>
      <variableLink>12</variableLink>
      <variableLink>14</variableLink>
    </variables>
    <value>-0.000100225035</value>
  </coefficient>
  <coefficient>
    <variables>
      <variableLink>12</variableLink>
      <variableLink>15</variableLink>
    </variables>
    <value>-7.51479107e-005</value>
  </coefficient>
  <coefficient>
    <variables>
      <variableLink>12</variableLink>
      <variableLink>16</variableLink>
    </variables>
    <value>-1.79751196e-005</value>
  </coefficient>
  <coefficient>
    <variables>
      <variableLink>12</variableLink>
      <variableLink>17</variableLink>
    </variables>
    <value>3.1272044e-005</value>
  </coefficient>
  <coefficient>
    <variables>
      <variableLink>13</variableLink>
      <variableLink>13</variableLink>
    </variables>
    <value>-0.0012796897</value>
  </coefficient>
  <coefficient>
    <variables>
      <variableLink>13</variableLink>
      <variableLink>14</variableLink>
    </variables>
    <value>-3.20761454e-005</value>
  </coefficient>
  <coefficient>
    <variables>
      <variableLink>13</variableLink>
      <variableLink>15</variableLink>
    </variables>
    <value>-3.22806262e-005</value>
  </coefficient>
  <coefficient>
    <variables>
      <variableLink>13</variableLink>
      <variableLink>16</variableLink>
    </variables>
    <value>-3.21871392e-005</value>
  </coefficient>
  <coefficient>
    <variables>
      <variableLink>13</variableLink>
      <variableLink>17</variableLink>
    </variables>
    <value>-0.000623963364</value>
  </coefficient>
  <coefficient>
    <variables>
      <variableLink>14</variableLink>
      <variableLink>14</variableLink>
    </variables>
    <value>-0.00021787669</value>
  </coefficient>
  <coefficient>
    <variables>
      <variableLink>14</variableLink>
      <variableLink>15</variableLink>
    </variables>
    <value>6.98943529e-005</value>
  </coefficient>
  <coefficient>
    <variables>
      <variableLink>14</variableLink>
      <variableLink>16</variableLink>
    </variables>
    <value>2.96615107e-005</value>
  </coefficient>
  <coefficient>
    <variables>
      <variableLink>14</variableLink>
      <variableLink>17</variableLink>
    </variables>
    <value>0.000276773332</value>
  </coefficient>
  <coefficient>
    <variables>
      <variableLink>15</variableLink>
      <variableLink>15</variableLink>
    </variables>
    <value>-3.54876311e-005</value>
  </coefficient>
  <coefficient>
    <variables>
      <variableLink>15</variableLink>
      <variableLink>16</variableLink>
    </variables>
    <value>-0.00010491102</value>
  </coefficient>
  <coefficient>
    <variables>
      <variableLink>15</variableLink>
      <variableLink>17</variableLink>
    </variables>
    <value>1.81055726e-005</value>
  </coefficient>
  <coefficient>
    <variables>
      <variableLink>16</variableLink>
      <variableLink>16</variableLink>
    </variables>
    <value>1.12144816e-005</value>
  </coefficient>
  <coefficient>
    <variables>
      <variableLink>16</variableLink>
      <variableLink>17</variableLink>
    </variables>
    <value>-8.24459721e-005</value>
  </coefficient>
  <coefficient>
    <variables>
      <variableLink>17</variableLink>
      <variableLink>17</variableLink>
    </variables>
    <value>-0.00438465257</value>
  </coefficient>
  <additionalDataItem itemType="text" description="surrogateModel description">
      The rates of H2 consumption from 60 to 40% of the initial value in a turbulent flow reactor.
   </additionalDataItem>
</surrogateModel>